design.sv
// Code your design here
module fifo_synchronous #(parameter DEPTH=8 ,WIDTH = 8) (input clk,rst_n,w_en,r_en,                                              input [WIDTH-1:0] data_in,output reg [WIDTH-1:0] data_out, output full,empty);
  
  reg [$clog2(DEPTH)-1:0] w_ptr,r_ptr;
  reg [WIDTH-1:0] fifo[DEPTH];
  
  
  //Default Reset Values
  always@(posedge clk) begin
    if(!rst_n) begin
      w_ptr<=0; r_ptr<=0;
      data_out<=0;
      for(int j=0;j<8;j++) begin
        fifo[j]<=0;
      end
    end
    
    else begin 
      	//Write operation
		if(w_en & !full) begin
      		fifo[w_ptr] <= data_in;
          w_ptr<=(w_ptr+1) % DEPTH;
    	end
    	//Read operation
    	if(r_en & !empty) begin
      		data_out<= fifo[r_ptr];
          r_ptr<= (r_ptr+1) % DEPTH;
    	end
  	end
    
  end
  
  assign full = ((w_ptr==3'b111 & r_ptr == 3'b000));
//   assign full = ((w_ptr[3] ^ r_ptr[3]) & (w_ptr == r_ptr));
  assign empty = (r_ptr==w_ptr);
  
endmodule

testbench.sv
// Code your testbench here
// or browse Examples
module tb_sync_fifo;
  parameter DEPTH = 8;
  parameter WIDTH = 8;
  
  wire [WIDTH-1:0] data_out;
  wire full,empty;
  reg clk,rst_n,w_en,r_en;
  reg [WIDTH-1:0] data_in;
  
  //We need a Queue to push data_in
  
  reg [WIDTH-1:0] data_queue[$], wdata;
  
  fifo_synchronous fifo_instance(clk,rst_n,w_en,r_en,data_in,data_out,full,empty);
  
  
  always #5 clk = ~clk;
  
  // Reset COndition
  initial begin
    clk=0;rst_n=0;w_en=0;data_in=0;
  end
  
  
  
  initial begin
    // Write Operation
    repeat(2) @(posedge clk); //Wait for 10 CLK Cycles
    rst_n=1; //Remove reset signal
    
    repeat(1) begin
      for (int i=0;i<30;i=i+1) begin
        @(posedge clk);
        w_en = (i%2 == 0) ? 1 : 0 ;
        if (w_en & !full) begin
          data_in = $urandom; // data being given to DUT
          data_queue.push_back(data_in); //same data being fed to queu for later comparison
        end
      end  
    end
    
    //Read Operation
    repeat(5) @(posedge clk); //Start reading after 5 CLK Cycles
    
    repeat(1) begin
      for(int i =0;i<30;i++) begin
        @(posedge clk);
        r_en = (i%2 == 0) ? 1: 0;
        if (r_en & !empty) begin
          #1;
          wdata = data_queue.pop_front();
          if(data_out != wdata)
            $error("Time = %0t: Comparison Failed : Expected wrData = %h, received_data = %h",$time,wdata,data_out);
          else
            $display("Time = %0t: Comparison Passed: wr_data = %h and rd_data = %h",$time,wdata,data_out);
        end
      end
    end
    
    $finish();
  end
    

  
  
  
    
    
    
    
    
  
  initial begin
    $dumpfile("sync_fifo_hdk.vcd");
    $dumpvars;
  end
  
endmodule

sync_fifo_hdk.vcd
$date
	Sun Jun 23 12:58:22 2024
$end

$version
	Synopsys VCS version U-2023.03-SP2_Full64
$end

$timescale
	1ns
$end

$comment Csum: 1 c017cda8aaaeaf8b $end


$scope module tb_sync_fifo $end
$var wire 8 ! data_out [7:0] $end
$var wire 1 " full $end
$var wire 1 # empty $end
$var reg 1 $ clk $end
$var reg 1 % rst_n $end
$var reg 1 & w_en $end
$var reg 1 ' r_en $end
$var reg 8 ( data_in [7:0] $end
$var reg 8 ) wdata [7:0] $end

$scope begin unnamed$$_vcs_3 $end
$upscope $end


$scope begin unnamed$$_vcs_0 $end
$upscope $end


$scope begin unnamed$$_vcs_1 $end
$upscope $end


$scope begin unnamed$$_vcs_2 $end

$scope begin unnamed$$_0 $end
$upscope $end


$scope begin unnamed$$_1 $end
$upscope $end

$upscope $end


$scope module fifo_instance $end
$var wire 1 $ clk $end
$var wire 1 % rst_n $end
$var wire 1 & w_en $end
$var wire 1 ' r_en $end
$var wire 8 ( data_in [7:0] $end
$var reg 8 ! data_out [7:0] $end
$var wire 1 " full $end
$var wire 1 # empty $end
$var reg 3 * w_ptr [2:0] $end
$var reg 3 + r_ptr [2:0] $end

$scope begin unnamed$$_0 $end
$upscope $end

$upscope $end

$upscope $end

$enddefinitions $end

#0
$dumpvars
0$
x#
x"
x'
0%
0&
b00000000 (
bxxxxxxxx !
bxxx +
bxxx *
bxxxxxxxx )
$end
#5
1$
b000 *
0"
1#
b000 +
b00000000 !
#10
0$
#15
1$
1%
#20
0$
#25
1$
1&
b01010001 (
b001 *
0#
#30
0$
#35
1$
0&
#40
0$
#45
1$
1&
b11001101 (
b010 *
#50
0$
#55
1$
0&
#60
0$
#65
1$
1&
b00001110 (
b011 *
#70
0$
#75
1$
0&
#80
0$
#85
1$
1&
b11011011 (
b100 *
#90
0$
#95
1$
0&
#100
0$
#105
1$
1&
b01110001 (
b101 *
#110
0$
#115
1$
0&
#120
0$
#125
1$
1&
b01100011 (
b110 *
#130
0$
#135
1$
0&
#140
0$
#145
1$
1&
b11101001 (
b111 *
1"
#150
0$
#155
1$
0&
#160
0$
#165
1$
1&
#170
0$
#175
1$
0&
#180
0$
#185
1$
1&
#190
0$
#195
1$
0&
#200
0$
#205
1$
1&
#210
0$
#215
1$
0&
#220
0$
#225
1$
1&
#230
0$
#235
1$
0&
#240
0$
#245
1$
1&
#250
0$
#255
1$
0&
#260
0$
#265
1$
1&
#270
0$
#275
1$
0&
#280
0$
#285
1$
1&
#290
0$
#295
1$
0&
#300
0$
#305
1$
1&
#310
0$
#315
1$
0&
#320
0$
#325
1$
#330
0$
#335
1$
#340
0$
#345
1$
#350
0$
#355
1$
#360
0$
#365
1$
#370
0$
#375
1$
1'
b01010001 !
b001 +
0"
#376
b01010001 )
#380
0$
#385
1$
0'
#390
0$
#395
1$
1'
b11001101 !
b010 +
#396
b11001101 )
#400
0$
#405
1$
0'
#410
0$
#415
1$
1'
b00001110 !
b011 +
#416
b00001110 )
#420
0$
#425
1$
0'
#430
0$
#435
1$
1'
b11011011 !
b100 +
#436
b11011011 )
#440
0$
#445
1$
0'
#450
0$
#455
1$
1'
b01110001 !
b101 +
#456
b01110001 )
#460
0$
#465
1$
0'
#470
0$
#475
1$
1'
b01100011 !
b110 +
#476
b01100011 )
#480
0$
#485
1$
0'
#490
0$
#495
1$
1'
b11101001 !
b111 +
1#
#496
b11101001 )
#500
0$
#505
1$
0'
#510
0$
#515
1$
1'
#520
0$
#525
1$
0'
#530
0$
#535
1$
1'
#540
0$
#545
1$
0'
#550
0$
#555
1$
1'
#560
0$
#565
1$
0'
#570
0$
#575
1$
1'
#580
0$
#585
1$
0'
#590
0$
#595
1$
1'
#600
0$
#605
1$
0'
#610
0$
#615
1$
1'
#620
0$
#625
1$
0'
#630
0$
#635
1$
1'
#640
0$
#645
1$
0'
#650
0$
#655
1$
1'
#660
0$
#665
1$
0'
